metaffi/__init__.py
metaffi/classes_metaffi.puml
metaffi/metaffi_module.py
metaffi/metaffi_runtime.py
metaffi/metaffi_types.py
metaffi/metaffihandle.py
metaffi/pycdts_converter.py
metaffi/xllr_wrapper.py
metaffi_api-0.0.71.dist-info/licenses/LICENSE
metaffi_api-0.0.71.dist-info/WHEEL
metaffi_api-0.0.71.dist-info/METADATA
metaffi_api-0.0.71.dist-info/RECORD
