Metadata-Version: 2.4
Name: metaffi-api
Version: 0.0.71
Summary: Python MetaFFI API
Author: T. CS.
Requires-Python: >=3.11
Classifier: Programming Language :: Python :: 3
Classifier: License :: OSI Approved :: MIT License
Classifier: Operating System :: OS Independent
Classifier: Topic :: Software Development
License-File: LICENSE
Project-URL: Home, https://github.com/MetaFFI/MetaFFI/
